repli/__init__.py
repli/callback.py
repli/command.py
repli/console.py
repli/interpreter.py
repli-0.2.7.dist-info/LICENSE
repli-0.2.7.dist-info/METADATA
repli-0.2.7.dist-info/WHEEL
repli-0.2.7.dist-info/entry_points.txt
repli-0.2.7.dist-info/RECORD
