Metadata-Version: 2.3
Name: repli
Version: 0.2.7
Summary: Read–Eval–Print Loop Interpreter
Author: luojiahai
Author-email: luo@jiahai.co
Requires-Python: >=3.12,<4.0
Classifier: Programming Language :: Python :: 3
Classifier: Programming Language :: Python :: 3.12
Classifier: Programming Language :: Python :: 3.13
Requires-Dist: rich (>=13.9.4,<14.0.0)
